{"match_id": "mt_740177236", "coverage": "full", "events": [{"sequence": 1, "minute": 1, "extra_time": 0, "period": "first_half", "type": "period_start", "team": null, "player": null}, {"sequence": 2, "minute": 6, "extra_time": 0, "period": "first_half", "type": "shot_off_target", "team": {"id": "tm_28025", "name": "Algeria", "slug": "algeria-tm_28025"}, "player": {"id": "pl_29752763", "name": "Houssem Aouar", "slug": "houssem-aouar-pl_29752763"}}, {"sequence": 3, "minute": 10, "extra_time": 0, "period": "first_half", "type": "goal", "team": {"id": "tm_70912", "name": "Switzerland", "slug": "switzerland-tm_70912"}, "player": {"id": "pl_6965248", "name": "Breel Embolo", "slug": "breel-embolo-pl_6965248"}}, {"sequence": 4, "minute": 12, "extra_time": 0, "period": "first_half", "type": "foul", "team": {"id": "tm_70912", "name": "Switzerland", "slug": "switzerland-tm_70912"}, "player": {"id": "pl_7224757", "name": "Ricardo Rodr\u00edguez", "slug": "ricardo-rodriguez-pl_7224757"}}, {"sequence": 5, "minute": 14, "extra_time": 0, "period": "first_half", "type": "shot_on_target", "team": {"id": "tm_28025", "name": "Algeria", "slug": "algeria-tm_28025"}, "player": {"id": "pl_29752763", "name": "Houssem Aouar", "slug": "houssem-aouar-pl_29752763"}}, {"sequence": 6, "minute": 15, "extra_time": 0, "period": "first_half", "type": "shot_on_target", "team": {"id": "tm_70912", "name": "Switzerland", "slug": "switzerland-tm_70912"}, "player": {"id": "pl_30858084", "name": "Denis Zakaria", "slug": "denis-zakaria-pl_30858084"}}, {"sequence": 7, "minute": 18, "extra_time": 0, "period": "first_half", "type": "shot_blocked", "team": {"id": "tm_28025", "name": "Algeria", "slug": "algeria-tm_28025"}, "player": {"id": "pl_01354953", "name": "Ibrahim Maza", "slug": "ibrahim-maza-pl_01354953"}}, {"sequence": 8, "minute": 21, "extra_time": 0, "period": "first_half", "type": "foul", "team": {"id": "tm_28025", "name": "Algeria", "slug": "algeria-tm_28025"}, "player": {"id": "pl_96343349", "name": "Ramiz Zerrouki", "slug": "ramiz-zerrouki-pl_96343349"}}, {"sequence": 9, "minute": 22, "extra_time": 0, "period": "first_half", "type": "corner_kick", "team": {"id": "tm_28025", "name": "Algeria", "slug": "algeria-tm_28025"}, "player": {"id": "pl_83264637", "name": "Rafik Belghali", "slug": "rafik-belghali-pl_83264637"}}, {"sequence": 10, "minute": 25, "extra_time": 0, "period": "first_half", "type": "shot_off_target", "team": {"id": "tm_70912", "name": "Switzerland", "slug": "switzerland-tm_70912"}, "player": {"id": "pl_7224757", "name": "Ricardo Rodr\u00edguez", "slug": "ricardo-rodriguez-pl_7224757"}}, {"sequence": 11, "minute": 31, "extra_time": 0, "period": "first_half", "type": "foul", "team": {"id": "tm_28025", "name": "Algeria", "slug": "algeria-tm_28025"}, "player": {"id": "pl_84668539", "name": "Rayan A\u00eft-Nouri", "slug": "rayan-ait-nouri-pl_84668539"}}, {"sequence": 12, "minute": 33, "extra_time": 0, "period": "first_half", "type": "foul", "team": {"id": "tm_70912", "name": "Switzerland", "slug": "switzerland-tm_70912"}, "player": {"id": "pl_72561361", "name": "Rub\u00e9n Vargas", "slug": "ruben-vargas-pl_72561361"}}, {"sequence": 13, "minute": 33, "extra_time": 0, "period": "first_half", "type": "foul", "team": {"id": "tm_28025", "name": "Algeria", "slug": "algeria-tm_28025"}, "player": {"id": "pl_84668539", "name": "Rayan A\u00eft-Nouri", "slug": "rayan-ait-nouri-pl_84668539"}}, {"sequence": 14, "minute": 35, "extra_time": 0, "period": "first_half", "type": "foul", "team": {"id": "tm_70912", "name": "Switzerland", "slug": "switzerland-tm_70912"}, "player": {"id": "pl_6169311", "name": "Remo Freuler", "slug": "remo-freuler-pl_6169311"}}, {"sequence": 15, "minute": 36, "extra_time": 0, "period": "first_half", "type": "foul", "team": {"id": "tm_28025", "name": "Algeria", "slug": "algeria-tm_28025"}, "player": {"id": "pl_83346587", "name": "Far\u00e8s Cha\u00efbi", "slug": "fares-chaibi-pl_83346587"}}, {"sequence": 16, "minute": 36, "extra_time": 0, "period": "first_half", "type": "yellow_card", "team": {"id": "tm_28025", "name": "Algeria", "slug": "algeria-tm_28025"}, "player": {"id": "pl_83346587", "name": "Far\u00e8s Cha\u00efbi", "slug": "fares-chaibi-pl_83346587"}}, {"sequence": 17, "minute": 37, "extra_time": 0, "period": "first_half", "type": "shot_off_target", "team": {"id": "tm_70912", "name": "Switzerland", "slug": "switzerland-tm_70912"}, "player": {"id": "pl_30858084", "name": "Denis Zakaria", "slug": "denis-zakaria-pl_30858084"}}, {"sequence": 18, "minute": 38, "extra_time": 0, "period": "first_half", "type": "foul", "team": {"id": "tm_70912", "name": "Switzerland", "slug": "switzerland-tm_70912"}, "player": {"id": "pl_30233776", "name": "Dan Ndoye", "slug": "dan-ndoye-pl_30233776"}}, {"sequence": 19, "minute": 38, "extra_time": 0, "period": "first_half", "type": "foul", "team": {"id": "tm_28025", "name": "Algeria", "slug": "algeria-tm_28025"}, "player": {"id": "pl_1794179", "name": "Nabil Bentaleb", "slug": "nabil-bentaleb-pl_1794179"}}, {"sequence": 20, "minute": 39, "extra_time": 0, "period": "first_half", "type": "corner_kick", "team": {"id": "tm_28025", "name": "Algeria", "slug": "algeria-tm_28025"}, "player": {"id": "pl_1947036", "name": "A\u00efssa Mandi", "slug": "aissa-mandi-pl_1947036"}}, {"sequence": 21, "minute": 41, "extra_time": 0, "period": "first_half", "type": "corner_kick", "team": {"id": "tm_70912", "name": "Switzerland", "slug": "switzerland-tm_70912"}, "player": {"id": "pl_7224757", "name": "Ricardo Rodr\u00edguez", "slug": "ricardo-rodriguez-pl_7224757"}}, {"sequence": 22, "minute": 43, "extra_time": 0, "period": "first_half", "type": "foul", "team": {"id": "tm_70912", "name": "Switzerland", "slug": "switzerland-tm_70912"}, "player": {"id": "pl_25186759", "name": "Johan Manzambi", "slug": "johan-manzambi-pl_25186759"}}, {"sequence": 23, "minute": 43, "extra_time": 0, "period": "first_half", "type": "shot_on_target", "team": {"id": "tm_28025", "name": "Algeria", "slug": "algeria-tm_28025"}, "player": {"id": "pl_83346587", "name": "Far\u00e8s Cha\u00efbi", "slug": "fares-chaibi-pl_83346587"}}, {"sequence": 24, "minute": 45, "extra_time": 1, "period": "first_half", "type": "added_time", "team": null, "player": null}, {"sequence": 25, "minute": 45, "extra_time": 2, "period": "first_half", "type": "shot_off_target", "team": {"id": "tm_28025", "name": "Algeria", "slug": "algeria-tm_28025"}, "player": {"id": "pl_01354953", "name": "Ibrahim Maza", "slug": "ibrahim-maza-pl_01354953"}}, {"sequence": 26, "minute": 45, "extra_time": 3, "period": "first_half", "type": "offside", "team": {"id": "tm_28025", "name": "Algeria", "slug": "algeria-tm_28025"}, "player": {"id": "pl_5837688", "name": "Riyad Mahrez", "slug": "riyad-mahrez-pl_5837688"}}, {"sequence": 27, "minute": 45, "extra_time": 3, "period": "first_half", "type": "period_end", "team": null, "player": null}, {"sequence": 28, "minute": 46, "extra_time": 0, "period": "second_half", "type": "period_start", "team": null, "player": null}, {"sequence": 29, "minute": 46, "extra_time": 0, "period": "second_half", "type": "goal", "team": {"id": "tm_70912", "name": "Switzerland", "slug": "switzerland-tm_70912"}, "player": {"id": "pl_30233776", "name": "Dan Ndoye", "slug": "dan-ndoye-pl_30233776"}}, {"sequence": 30, "minute": 50, "extra_time": 0, "period": "second_half", "type": "shot_blocked", "team": {"id": "tm_28025", "name": "Algeria", "slug": "algeria-tm_28025"}, "player": {"id": "pl_5837688", "name": "Riyad Mahrez", "slug": "riyad-mahrez-pl_5837688"}}, {"sequence": 31, "minute": 52, "extra_time": 0, "period": "second_half", "type": "foul", "team": {"id": "tm_28025", "name": "Algeria", "slug": "algeria-tm_28025"}, "player": {"id": "pl_96343349", "name": "Ramiz Zerrouki", "slug": "ramiz-zerrouki-pl_96343349"}}, {"sequence": 32, "minute": 55, "extra_time": 0, "period": "second_half", "type": "foul", "team": {"id": "tm_28025", "name": "Algeria", "slug": "algeria-tm_28025"}, "player": {"id": "pl_1794179", "name": "Nabil Bentaleb", "slug": "nabil-bentaleb-pl_1794179"}}, {"sequence": 33, "minute": 57, "extra_time": 0, "period": "second_half", "type": "foul", "team": {"id": "tm_28025", "name": "Algeria", "slug": "algeria-tm_28025"}, "player": {"id": "pl_01354953", "name": "Ibrahim Maza", "slug": "ibrahim-maza-pl_01354953"}}, {"sequence": 34, "minute": 58, "extra_time": 0, "period": "second_half", "type": "substitution", "team": {"id": "tm_28025", "name": "Algeria", "slug": "algeria-tm_28025"}, "player": {"id": "pl_08090980", "name": "Jaouen Hadjam", "slug": "jaouen-hadjam-pl_08090980"}}, {"sequence": 35, "minute": 59, "extra_time": 0, "period": "second_half", "type": "substitution", "team": {"id": "tm_28025", "name": "Algeria", "slug": "algeria-tm_28025"}, "player": {"id": "pl_61936424", "name": "Amine Gouiri", "slug": "amine-gouiri-pl_61936424"}}, {"sequence": 36, "minute": 60, "extra_time": 0, "period": "second_half", "type": "corner_kick", "team": {"id": "tm_28025", "name": "Algeria", "slug": "algeria-tm_28025"}, "player": {"id": "pl_1794179", "name": "Nabil Bentaleb", "slug": "nabil-bentaleb-pl_1794179"}}, {"sequence": 37, "minute": 65, "extra_time": 0, "period": "second_half", "type": "corner_kick", "team": {"id": "tm_28025", "name": "Algeria", "slug": "algeria-tm_28025"}, "player": {"id": "pl_1947036", "name": "A\u00efssa Mandi", "slug": "aissa-mandi-pl_1947036"}}, {"sequence": 38, "minute": 65, "extra_time": 0, "period": "second_half", "type": "foul", "team": {"id": "tm_70912", "name": "Switzerland", "slug": "switzerland-tm_70912"}, "player": {"id": "pl_7224757", "name": "Ricardo Rodr\u00edguez", "slug": "ricardo-rodriguez-pl_7224757"}}, {"sequence": 39, "minute": 65, "extra_time": 0, "period": "second_half", "type": "shot_blocked", "team": {"id": "tm_70912", "name": "Switzerland", "slug": "switzerland-tm_70912"}, "player": {"id": "pl_7961246", "name": "Nico Elvedi", "slug": "nico-elvedi-pl_7961246"}}, {"sequence": 40, "minute": 71, "extra_time": 0, "period": "second_half", "type": "substitution", "team": {"id": "tm_70912", "name": "Switzerland", "slug": "switzerland-tm_70912"}, "player": {"id": "pl_57445828", "name": "Noah Okafor", "slug": "noah-okafor-pl_57445828"}}, {"sequence": 41, "minute": 71, "extra_time": 0, "period": "second_half", "type": "substitution", "team": {"id": "tm_70912", "name": "Switzerland", "slug": "switzerland-tm_70912"}, "player": {"id": "pl_13777383", "name": "Fabian Rieder", "slug": "fabian-rieder-pl_13777383"}}, {"sequence": 42, "minute": 71, "extra_time": 0, "period": "second_half", "type": "substitution", "team": {"id": "tm_28025", "name": "Algeria", "slug": "algeria-tm_28025"}, "player": {"id": "pl_62299005", "name": "Anis Hadj Moussa", "slug": "anis-hadj-moussa-pl_62299005"}}, {"sequence": 43, "minute": 71, "extra_time": 0, "period": "second_half", "type": "substitution", "team": {"id": "tm_28025", "name": "Algeria", "slug": "algeria-tm_28025"}, "player": {"id": "pl_57938156", "name": "Hicham Boudaoui", "slug": "hicham-boudaoui-pl_57938156"}}, {"sequence": 44, "minute": 72, "extra_time": 0, "period": "second_half", "type": "yellow_card", "team": {"id": "tm_28025", "name": "Algeria", "slug": "algeria-tm_28025"}, "player": {"id": "pl_57938156", "name": "Hicham Boudaoui", "slug": "hicham-boudaoui-pl_57938156"}}, {"sequence": 45, "minute": 72, "extra_time": 0, "period": "second_half", "type": "foul", "team": {"id": "tm_28025", "name": "Algeria", "slug": "algeria-tm_28025"}, "player": {"id": "pl_57938156", "name": "Hicham Boudaoui", "slug": "hicham-boudaoui-pl_57938156"}}, {"sequence": 46, "minute": 75, "extra_time": 0, "period": "second_half", "type": "shot_blocked", "team": {"id": "tm_70912", "name": "Switzerland", "slug": "switzerland-tm_70912"}, "player": {"id": "pl_13777383", "name": "Fabian Rieder", "slug": "fabian-rieder-pl_13777383"}}, {"sequence": 47, "minute": 76, "extra_time": 0, "period": "second_half", "type": "corner_kick", "team": {"id": "tm_70912", "name": "Switzerland", "slug": "switzerland-tm_70912"}, "player": {"id": "pl_7224757", "name": "Ricardo Rodr\u00edguez", "slug": "ricardo-rodriguez-pl_7224757"}}, {"sequence": 48, "minute": 77, "extra_time": 0, "period": "second_half", "type": "shot_off_target", "team": {"id": "tm_28025", "name": "Algeria", "slug": "algeria-tm_28025"}, "player": {"id": "pl_08090980", "name": "Jaouen Hadjam", "slug": "jaouen-hadjam-pl_08090980"}}, {"sequence": 49, "minute": 78, "extra_time": 0, "period": "second_half", "type": "foul", "team": {"id": "tm_28025", "name": "Algeria", "slug": "algeria-tm_28025"}, "player": {"id": "pl_83264637", "name": "Rafik Belghali", "slug": "rafik-belghali-pl_83264637"}}, {"sequence": 50, "minute": 80, "extra_time": 0, "period": "second_half", "type": "shot_off_target", "team": {"id": "tm_70912", "name": "Switzerland", "slug": "switzerland-tm_70912"}, "player": {"id": "pl_6965248", "name": "Breel Embolo", "slug": "breel-embolo-pl_6965248"}}, {"sequence": 51, "minute": 81, "extra_time": 0, "period": "second_half", "type": "foul", "team": {"id": "tm_70912", "name": "Switzerland", "slug": "switzerland-tm_70912"}, "player": {"id": "pl_6169311", "name": "Remo Freuler", "slug": "remo-freuler-pl_6169311"}}, {"sequence": 52, "minute": 81, "extra_time": 0, "period": "second_half", "type": "shot_off_target", "team": {"id": "tm_70912", "name": "Switzerland", "slug": "switzerland-tm_70912"}, "player": {"id": "pl_13777383", "name": "Fabian Rieder", "slug": "fabian-rieder-pl_13777383"}}, {"sequence": 53, "minute": 82, "extra_time": 0, "period": "second_half", "type": "substitution", "team": {"id": "tm_28025", "name": "Algeria", "slug": "algeria-tm_28025"}, "player": {"id": "pl_97013866", "name": "Adil Boulbina", "slug": "adil-boulbina-pl_97013866"}}, {"sequence": 54, "minute": 83, "extra_time": 0, "period": "second_half", "type": "foul", "team": {"id": "tm_70912", "name": "Switzerland", "slug": "switzerland-tm_70912"}, "player": {"id": "pl_7224757", "name": "Ricardo Rodr\u00edguez", "slug": "ricardo-rodriguez-pl_7224757"}}, {"sequence": 55, "minute": 83, "extra_time": 0, "period": "second_half", "type": "substitution", "team": {"id": "tm_70912", "name": "Switzerland", "slug": "switzerland-tm_70912"}, "player": {"id": "pl_13871843", "name": "Zeki Amdouni", "slug": "zeki-amdouni-pl_13871843"}}, {"sequence": 56, "minute": 86, "extra_time": 0, "period": "second_half", "type": "foul", "team": {"id": "tm_70912", "name": "Switzerland", "slug": "switzerland-tm_70912"}, "player": {"id": "pl_13871843", "name": "Zeki Amdouni", "slug": "zeki-amdouni-pl_13871843"}}, {"sequence": 57, "minute": 87, "extra_time": 0, "period": "second_half", "type": "substitution", "team": {"id": "tm_70912", "name": "Switzerland", "slug": "switzerland-tm_70912"}, "player": {"id": "pl_3613437", "name": "Silvan Widmer", "slug": "silvan-widmer-pl_3613437"}}, {"sequence": 58, "minute": 87, "extra_time": 0, "period": "second_half", "type": "substitution", "team": {"id": "tm_70912", "name": "Switzerland", "slug": "switzerland-tm_70912"}, "player": {"id": "pl_29708916", "name": "Michel Aebischer", "slug": "michel-aebischer-pl_29708916"}}, {"sequence": 59, "minute": 88, "extra_time": 0, "period": "second_half", "type": "offside", "team": {"id": "tm_28025", "name": "Algeria", "slug": "algeria-tm_28025"}, "player": {"id": "pl_97013866", "name": "Adil Boulbina", "slug": "adil-boulbina-pl_97013866"}}, {"sequence": 60, "minute": 90, "extra_time": 0, "period": "second_half", "type": "foul", "team": {"id": "tm_28025", "name": "Algeria", "slug": "algeria-tm_28025"}, "player": {"id": "pl_83346587", "name": "Far\u00e8s Cha\u00efbi", "slug": "fares-chaibi-pl_83346587"}}, {"sequence": 61, "minute": 90, "extra_time": 1, "period": "second_half", "type": "added_time", "team": null, "player": null}, {"sequence": 62, "minute": 90, "extra_time": 2, "period": "second_half", "type": "foul", "team": {"id": "tm_70912", "name": "Switzerland", "slug": "switzerland-tm_70912"}, "player": {"id": "pl_13777383", "name": "Fabian Rieder", "slug": "fabian-rieder-pl_13777383"}}, {"sequence": 63, "minute": 90, "extra_time": 3, "period": "second_half", "type": "foul", "team": {"id": "tm_28025", "name": "Algeria", "slug": "algeria-tm_28025"}, "player": {"id": "pl_57938156", "name": "Hicham Boudaoui", "slug": "hicham-boudaoui-pl_57938156"}}, {"sequence": 64, "minute": 90, "extra_time": 3, "period": "second_half", "type": "shot_blocked", "team": {"id": "tm_28025", "name": "Algeria", "slug": "algeria-tm_28025"}, "player": {"id": "pl_01354953", "name": "Ibrahim Maza", "slug": "ibrahim-maza-pl_01354953"}}]}